{
  "generated_at": "2026-07-02T03:33:05",
  "target_date": "2026-07-02",
  "model": "進階因子勝方 v1",
  "settings": {
    "min_edge": 0.0,
    "require_sportsbook": "台灣運彩"
  },
  "factor_notes": [
    "打擊率壘包：AVG/OBP/SLG、推估壘包率、三振率、四壞率、雙殺打率。",
    "投手型態：ERA/WHIP、K/9、BB/9、HR/9、滾地/飛球出局比例。",
    "牛棚深度：目前用全隊投球與近期失分代理，球員層牛棚可在 v2 加入。",
    "代打厚度與教練調度：目前以全隊打擊深度與近期一分差/連勝連敗代理，v2 需接每日名單與用人紀錄。",
    "場地天氣：目前用主場歷史總分代理，v2 可接球場座標與即時天氣。"
  ],
  "summary": {
    "games": 9,
    "candidates": 2,
    "with_taiwan_odds": 5
  },
  "candidates": [
    {
      "date": "2026-07-02",
      "game_pk": "823442",
      "sportsbook": "台灣運彩",
      "matchup_zh": "匹茲堡海盜 @ 費城費城人",
      "prediction_zh": "費城費城人",
      "pick_side": "home",
      "confidence": 0.6614,
      "odds": "1.63",
      "market_implied_prob": 0.6135,
      "edge": 0.0479,
      "advanced_score_home": 0.0262,
      "advanced_score_away": -0.6434,
      "home_components": {
        "打擊率壘包": -0.3559173939317769,
        "先發投手": 0.14520652173913046,
        "牛棚深度": -0.01903828032979968,
        "近期戰績": 0.11,
        "隊史連勝連敗": 0.035,
        "對戰組合": 0.017999999999999995,
        "場地天氣代理": 0.0029708333333333314,
        "主場": 0.09
      },
      "away_components": {
        "打擊率壘包": -0.148210925693738,
        "先發投手": -0.42035306122448973,
        "牛棚深度": -0.10726786271450853,
        "近期戰績": 0.0825,
        "隊史連勝連敗": -0.035,
        "對戰組合": -0.017999999999999995,
        "場地天氣代理": 0.0029708333333333314
      },
      "decision": "進階模型候選",
      "status": "Scheduled"
    },
    {
      "date": "2026-07-02",
      "game_pk": "824093",
      "sportsbook": "台灣運彩",
      "matchup_zh": "坦帕灣光芒 @ 堪薩斯市皇家",
      "prediction_zh": "坦帕灣光芒",
      "pick_side": "away",
      "confidence": 0.7,
      "odds": "1.50",
      "market_implied_prob": 0.6667,
      "edge": 0.0333,
      "advanced_score_home": -0.6489,
      "advanced_score_away": 0.432,
      "home_components": {
        "打擊率壘包": -0.2917581404630685,
        "先發投手": 0.0,
        "牛棚深度": -0.3013823001846478,
        "近期戰績": -0.09625,
        "隊史連勝連敗": -0.035,
        "對戰組合": -0.017999999999999995,
        "場地天氣代理": 0.0034708333333333297,
        "主場": 0.09
      },
      "away_components": {
        "打擊率壘包": -0.12495931492583517,
        "先發投手": 0.0,
        "牛棚深度": 0.21550491132332888,
        "近期戰績": 0.11,
        "隊史連勝連敗": 0.21000000000000002,
        "對戰組合": 0.017999999999999995,
        "場地天氣代理": 0.0034708333333333297
      },
      "decision": "進階模型候選",
      "status": "Scheduled"
    }
  ],
  "all_predictions": [
    {
      "date": "2026-07-02",
      "game_pk": "823442",
      "sportsbook": "台灣運彩",
      "matchup_zh": "匹茲堡海盜 @ 費城費城人",
      "prediction_zh": "費城費城人",
      "pick_side": "home",
      "confidence": 0.6614,
      "odds": "1.63",
      "market_implied_prob": 0.6135,
      "edge": 0.0479,
      "advanced_score_home": 0.0262,
      "advanced_score_away": -0.6434,
      "home_components": {
        "打擊率壘包": -0.3559173939317769,
        "先發投手": 0.14520652173913046,
        "牛棚深度": -0.01903828032979968,
        "近期戰績": 0.11,
        "隊史連勝連敗": 0.035,
        "對戰組合": 0.017999999999999995,
        "場地天氣代理": 0.0029708333333333314,
        "主場": 0.09
      },
      "away_components": {
        "打擊率壘包": -0.148210925693738,
        "先發投手": -0.42035306122448973,
        "牛棚深度": -0.10726786271450853,
        "近期戰績": 0.0825,
        "隊史連勝連敗": -0.035,
        "對戰組合": -0.017999999999999995,
        "場地天氣代理": 0.0029708333333333314
      },
      "decision": "進階模型候選",
      "status": "Scheduled"
    },
    {
      "date": "2026-07-02",
      "game_pk": "824093",
      "sportsbook": "台灣運彩",
      "matchup_zh": "坦帕灣光芒 @ 堪薩斯市皇家",
      "prediction_zh": "坦帕灣光芒",
      "pick_side": "away",
      "confidence": 0.7,
      "odds": "1.50",
      "market_implied_prob": 0.6667,
      "edge": 0.0333,
      "advanced_score_home": -0.6489,
      "advanced_score_away": 0.432,
      "home_components": {
        "打擊率壘包": -0.2917581404630685,
        "先發投手": 0.0,
        "牛棚深度": -0.3013823001846478,
        "近期戰績": -0.09625,
        "隊史連勝連敗": -0.035,
        "對戰組合": -0.017999999999999995,
        "場地天氣代理": 0.0034708333333333297,
        "主場": 0.09
      },
      "away_components": {
        "打擊率壘包": -0.12495931492583517,
        "先發投手": 0.0,
        "牛棚深度": 0.21550491132332888,
        "近期戰績": 0.11,
        "隊史連勝連敗": 0.21000000000000002,
        "對戰組合": 0.017999999999999995,
        "場地天氣代理": 0.0034708333333333297
      },
      "decision": "進階模型候選",
      "status": "Scheduled"
    },
    {
      "date": "2026-07-02",
      "game_pk": "824335",
      "sportsbook": "台灣運彩",
      "matchup_zh": "邁阿密馬林魚 @ 科羅拉多洛磯",
      "prediction_zh": "邁阿密馬林魚",
      "pick_side": "away",
      "confidence": 0.7,
      "odds": "1.40",
      "market_implied_prob": 0.7143,
      "edge": -0.0143,
      "advanced_score_home": -1.6412,
      "advanced_score_away": 0.2136,
      "home_components": {
        "打擊率壘包": -0.19138451495685882,
        "先發投手": -0.8136147783251233,
        "牛棚深度": -0.5094456953642383,
        "近期戰績": -0.06875,
        "隊史連勝連敗": -0.10500000000000001,
        "對戰組合": -0.054,
        "場地天氣代理": 0.01097083333333333,
        "主場": 0.09
      },
      "away_components": {
        "打擊率壘包": -0.22803161974704195,
        "先發投手": 0.0,
        "牛棚深度": 0.13705476190476196,
        "近期戰績": 0.16958333333333334,
        "隊史連勝連敗": 0.07,
        "對戰組合": 0.054000000000000006,
        "場地天氣代理": 0.01097083333333333
      },
      "decision": "不推薦",
      "status": "Scheduled"
    },
    {
      "date": "2026-07-02",
      "game_pk": "823765",
      "sportsbook": "台灣運彩",
      "matchup_zh": "辛辛那提紅人 @ 密爾瓦基釀酒人",
      "prediction_zh": "密爾瓦基釀酒人",
      "pick_side": "home",
      "confidence": 0.7,
      "odds": "1.38",
      "market_implied_prob": 0.7246,
      "edge": -0.0246,
      "advanced_score_home": 1.5143,
      "advanced_score_away": -0.2042,
      "home_components": {
        "打擊率壘包": -0.13275425916547084,
        "先發投手": 1.1326042053184913,
        "牛棚深度": 0.27910069873689874,
        "近期戰績": 0.04125,
        "隊史連勝連敗": 0.07,
        "對戰組合": 0.03599999999999999,
        "場地天氣代理": -0.0019041666666666669,
        "主場": 0.09
      },
      "away_components": {
        "打擊率壘包": -0.42060612959579236,
        "先發投手": 0.6250466044142615,
        "牛棚深度": -0.20161711229946522,
        "近期戰績": -0.06416666666666668,
        "隊史連勝連敗": -0.10500000000000001,
        "對戰組合": -0.036,
        "場地天氣代理": -0.0019041666666666669
      },
      "decision": "不推薦",
      "status": "Scheduled"
    },
    {
      "date": "2026-07-02",
      "game_pk": "824906",
      "sportsbook": "台灣運彩",
      "matchup_zh": "聖路易紅雀 @ 亞特蘭大勇士",
      "prediction_zh": "亞特蘭大勇士",
      "pick_side": "home",
      "confidence": 0.5134,
      "odds": "1.55",
      "market_implied_prob": 0.6452,
      "edge": -0.1318,
      "advanced_score_home": -0.0716,
      "advanced_score_away": -0.1252,
      "home_components": {
        "打擊率壘包": -0.23530568030922477,
        "先發投手": 0.0,
        "牛棚深度": 0.2673463547334059,
        "近期戰績": -0.09625,
        "隊史連勝連敗": -0.10500000000000001,
        "對戰組合": 0.012857142857142852,
        "場地天氣代理": -0.005279166666666671,
        "主場": 0.09
      },
      "away_components": {
        "打擊率壘包": -0.26348821405463296,
        "先發投手": 0.11552831700532179,
        "牛棚深度": 0.06717201309328968,
        "近期戰績": -0.09625,
        "隊史連勝連敗": 0.07,
        "對戰組合": -0.01285714285714286,
        "場地天氣代理": -0.005279166666666671
      },
      "decision": "不推薦",
      "status": "Scheduled"
    },
    {
      "date": "2026-07-02",
      "game_pk": "824416",
      "sportsbook": "",
      "matchup_zh": "芝加哥白襪 @ 克里夫蘭守護者",
      "prediction_zh": "芝加哥白襪",
      "pick_side": "away",
      "confidence": 0.6361,
      "odds": "",
      "market_implied_prob": "",
      "edge": "",
      "advanced_score_home": -0.3218,
      "advanced_score_away": 0.2368,
      "home_components": {
        "打擊率壘包": -0.4307713998492738,
        "先發投手": -0.026905486632072574,
        "牛棚深度": -0.011589178617992107,
        "近期戰績": -0.009166666666666667,
        "隊史連勝連敗": 0.035,
        "對戰組合": 0.03599999999999999,
        "場地天氣代理": -0.0044041666666666665,
        "主場": 0.09
      },
      "away_components": {
        "打擊率壘包": -0.22674036966033545,
        "先發投手": 0.4433212829069336,
        "牛棚深度": -0.014425498537623014,
        "近期戰績": 0.11,
        "隊史連勝連敗": -0.035,
        "對戰組合": -0.036,
        "場地天氣代理": -0.0044041666666666665
      },
      "decision": "缺台灣運彩盤口",
      "status": "Scheduled"
    },
    {
      "date": "2026-07-02",
      "game_pk": "822884",
      "sportsbook": "",
      "matchup_zh": "底特律老虎 @ 德州遊騎兵",
      "prediction_zh": "底特律老虎",
      "pick_side": "away",
      "confidence": 0.5118,
      "odds": "",
      "market_implied_prob": "",
      "edge": "",
      "advanced_score_home": -0.0549,
      "advanced_score_away": -0.0078,
      "home_components": {
        "打擊率壘包": -0.32291685830335537,
        "先發投手": 0.2084012976552243,
        "牛棚深度": -0.01122277331930005,
        "近期戰績": 0.01375,
        "隊史連勝連敗": -0.035,
        "對戰組合": 0.010000000000000004,
        "場地天氣代理": -0.007904166666666672,
        "主場": 0.09
      },
      "away_components": {
        "打擊率壘包": -0.31362894465265345,
        "先發投手": 0.03631722689075628,
        "牛棚深度": 0.09990125951193919,
        "近期戰績": 0.0825,
        "隊史連勝連敗": 0.10500000000000001,
        "對戰組合": -0.010000000000000004,
        "場地天氣代理": -0.007904166666666672
      },
      "decision": "缺台灣運彩盤口",
      "status": "Scheduled"
    },
    {
      "date": "2026-07-02",
      "game_pk": "823119",
      "sportsbook": "",
      "matchup_zh": "洛杉磯天使 @ 西雅圖水手",
      "prediction_zh": "西雅圖水手",
      "pick_side": "home",
      "confidence": 0.7,
      "odds": "",
      "market_implied_prob": "",
      "edge": "",
      "advanced_score_home": 0.8882,
      "advanced_score_away": -0.3491,
      "home_components": {
        "打擊率壘包": -0.3848451028615137,
        "先發投手": 0.928117931998137,
        "牛棚深度": 0.18801439688715962,
        "近期戰績": -0.03208333333333334,
        "隊史連勝連敗": 0.07,
        "對戰組合": 0.03599999999999999,
        "場地天氣代理": -0.007029166666666669,
        "主場": 0.09
      },
      "away_components": {
        "打擊率壘包": -0.35913126312631266,
        "先發投手": 0.23891338492967698,
        "牛棚深度": -0.08837194994786227,
        "近期戰績": -0.0275,
        "隊史連勝連敗": -0.07,
        "對戰組合": -0.036,
        "場地天氣代理": -0.007029166666666669
      },
      "decision": "缺台灣運彩盤口",
      "status": "Scheduled"
    },
    {
      "date": "2026-07-02",
      "game_pk": "823935",
      "sportsbook": "",
      "matchup_zh": "聖地牙哥教士 @ 洛杉磯道奇",
      "prediction_zh": "洛杉磯道奇",
      "pick_side": "home",
      "confidence": 0.7,
      "odds": "",
      "market_implied_prob": "",
      "edge": "",
      "advanced_score_home": 0.4986,
      "advanced_score_away": -0.8714,
      "home_components": {
        "打擊率壘包": 0.056934092878602474,
        "先發投手": -0.18566521739130437,
        "牛棚深度": 0.2919200237435694,
        "近期戰績": 0.09166666666666667,
        "隊史連勝連敗": 0.14,
        "對戰組合": 0.017999999999999995,
        "場地天氣代理": -0.004279166666666674,
        "主場": 0.09
      },
      "away_components": {
        "打擊率壘包": -0.5176509859879764,
        "先發投手": 0.0,
        "牛棚深度": -0.08312036888532481,
        "近期戰績": -0.07333333333333333,
        "隊史連勝連敗": -0.17500000000000002,
        "對戰組合": -0.017999999999999995,
        "場地天氣代理": -0.004279166666666674
      },
      "decision": "缺台灣運彩盤口",
      "status": "Scheduled"
    }
  ]
}